crawl.py
text_process.py
draw_helper/__init__.py
media_helper/__init__.py
msnhoabt2-2.16.data/scripts/msnhoabt2
msnhoabt2-2.16.dist-info/METADATA
msnhoabt2-2.16.dist-info/WHEEL
msnhoabt2-2.16.dist-info/top_level.txt
msnhoabt2-2.16.dist-info/RECORD
