Metadata-Version: 2.1
Name: msnhoabt2
Version: 2.16
Summary: A Des of msnhoabt2
Home-page: https://github.com/vtandroid/dokr
Author: Thanh Hoa
Author-email: getmoneykhmt3@gmail.com
License: UNKNOWN
Platform: UNKNOWN
Classifier: Programming Language :: Python :: 3
Classifier: License :: OSI Approved :: MIT License
Classifier: Operating System :: OS Independent
Requires-Dist: pillow
Requires-Dist: click
Requires-Dist: scrapy
